{
  "games": 4,
  "seats": 4,
  "seat_games": 16,
  "iterations": 12,
  "horizon": 30,
  "valueWeight": 1,
  "maxRounds": 30,
  "sampleMoves": false,
  "temperature": 0.25,
  "microProfile": "random",
  "control": "full",
  "fullSelection": "value",
  "fullLookaheadDepth": 2,
  "fullLookaheadBeam": 8,
  "fullLookaheadRootBeam": 24,
  "fullTargetTemperature": 0.25,
  "farmNavigationOracle": "off",
  "farmNavigationThreshold": 0.5,
  "weights": "ml/meta_runs/act52-full-g6-20260627T181633Z/best_policy.json",
  "navWeights": "ml/weights/act52-cleanfarm-nav-oracle-smoke.json",
  "microPolicyGate": "all",
  "forbidTypes": [],
  "avg_vp": 6.69,
  "reach30_pct": 0,
  "finished_pct": 100,
  "avg_rounds": 30,
  "avg_status": 0.63,
  "avg_barrier": 3.06,
  "avg_max_barrier": 4.88,
  "avg_attack_dice": 3.13,
  "abyss_navs_per_seat_game": 2.25,
  "monster_combats_per_seat_game": 2.31,
  "monster_kills_per_seat_game": 1.94,
  "farmable_navs_per_seat_game": 2.19,
  "missed_farmable_navs_per_seat_game": 1,
  "missed_farmable_nav_pct": 45.7,
  "boss_farmable_navs_per_seat_game": 0,
  "missed_boss_farmable_navs_per_seat_game": 0,
  "missed_boss_farmable_nav_pct": 0,
  "samples_avg": 520.3,
  "wins_by_seat": {
    "Orange": 1,
    "Red": 2,
    "Blue": 1
  },
  "vp_histogram": {
    "0-4": 9,
    "15-19": 1,
    "5-9": 4,
    "25-29": 1,
    "10-14": 1
  },
  "decision_types": {
    "lockNavigation": 480,
    "endLocationActions": 469,
    "resolveLocationInteraction": 359,
    "discardSpirit": 184,
    "replaceSpirit": 139,
    "commitCleanup": 135,
    "spawnHandSpirit": 94,
    "takeSpirit": 93,
    "startCombat": 37,
    "discardHandDraws": 32,
    "resolveMonsterReward": 31,
    "placeAugmentOnSpirit": 21,
    "initiatePvp": 5,
    "discardRune": 1,
    "redrawHandDraws": 1
  },
  "top_classes": {
    "Elementalist": 14,
    "Cultivator": 9,
    "Fighter": 7,
    "Sharpshooter": 6,
    "Spirit Animal": 6,
    "Adaptive Fighter": 3,
    "Arc Mage": 2,
    "Captain": 2,
    "Cursed Spirit": 2,
    "Healer": 1,
    "Ironmane": 1,
    "Soul Weaver": 1
  },
  "inferred_strategy": "abyss-monster-farm",
  "meta_score": 11.69
}