{
  "summary": {
    "mode": "route-execution-counterfactual",
    "config": {
      "games": 1,
      "seats": 4,
      "maxRounds": 30,
      "maxWindows": 4,
      "cleanThreshold": 0.5,
      "firepowerThreshold": 0.5,
      "selectHorizon": 6,
      "horizons": [
        3,
        6
      ],
      "labelHorizon": 6,
      "source": "full-control",
      "profiles": [
        "paragon",
        "farmer",
        "farmer2",
        "hard"
      ],
      "forbidTypes": [
        "initiatePvp"
      ],
      "maxStatusLevel": 0,
      "plannerWeights": "ml/meta_runs/aux-head-act52-medium-20260627T222453Z/best_policy.json",
      "navWeights": "ml/meta_runs/routeq-nav-specialist-20260628T0305Z/best_policy.json",
      "microWeights": "ml/meta_runs/routeexecq-micro-20260628T0405Z/best_policy.json",
      "microPolicyGate": "location-interactions",
      "navigationPolicyGate": "unsafe-firepower",
      "plannerIterations": 8,
      "plannerHorizon": 8,
      "plannerValueWeight": 1
    },
    "scannedLocationWindows": 4,
    "windows": 4,
    "skippedSingleAction": 0,
    "avgBestScoreDelta": 0,
    "avgBestVpDelta": 0,
    "avgBestCleanOpportunityDelta": 0,
    "avgBestFirepowerOpportunityDelta": 0,
    "avgBestExpectedAttackDelta": 0,
    "avgBestBarrierDelta": 0,
    "avgBestSpiritAnimalDelta": 0,
    "destinations": {
      "Floral Patch": 4
    },
    "bestActions": {
      "Floral Patch:row0:trade:anyRelic->restoreBarrier+restoreBarrier+restoreBarrier": 2,
      "Floral Patch:row2:gain:free->rest": 2
    },
    "sourceActions": {
      "Floral Patch:row0:trade:anyRelic->restoreBarrier+restoreBarrier+restoreBarrier": 2,
      "Floral Patch:row2:gain:free->rest": 2
    },
    "heuristicActions": {
      "Floral Patch:row0:trade:anyRelic->restoreBarrier+restoreBarrier+restoreBarrier": 2,
      "Floral Patch:row2:gain:free->rest": 2
    }
  },
  "rows": [
    {
      "id": "g0-Red-r1-0",
      "game": 0,
      "seat": "Red",
      "round": 1,
      "destination": "Floral Patch",
      "playerVp": 0,
      "playerStatus": 0,
      "legalActions": 6,
      "heuristicAction": "Floral Patch:row0:trade:anyRelic->restoreBarrier+restoreBarrier+restoreBarrier",
      "bestAction": "Floral Patch:row0:trade:anyRelic->restoreBarrier+restoreBarrier+restoreBarrier",
      "bestScoreDelta": 0,
      "bestVpDelta": 0,
      "bestCleanOpportunityDelta": 0,
      "bestFirepowerOpportunityDelta": 0,
      "bestExpectedAttackDelta": 0,
      "bestBarrierDelta": 0,
      "bestSpiritAnimalDelta": 0,
      "branches": [
        {
          "action": "Floral Patch:row0:trade:anyRelic->restoreBarrier+restoreBarrier+restoreBarrier",
          "destination": "Floral Patch",
          "finalVp": 0,
          "finalStatus": 0,
          "kills": 0,
          "combats": 0,
          "combatOpportunities": 0,
          "cleanCombatOpportunities": 0,
          "firepowerCombatOpportunities": 0,
          "maxExpectedAttack": 0,
          "maxBarrier": 4,
          "maxCurrentBarrier": 4,
          "maxAttackDice": 0,
          "maxSpiritAnimal": 0,
          "maxCultivator": 0,
          "maxHealer": 0,
          "maxCleanKillProb": 0,
          "maxFirepowerKillProb": 0,
          "rounds": 6,
          "snapshots": {
            "3": {
              "vp": 0,
              "status": 0,
              "kills": 0,
              "cleanCombatOpportunities": 0,
              "firepowerCombatOpportunities": 0,
              "maxExpectedAttack": 0,
              "maxBarrier": 4,
              "maxCurrentBarrier": 4,
              "maxAttackDice": 0,
              "maxSpiritAnimal": 0,
              "maxCultivator": 0,
              "round": 4
            },
            "6": {
              "vp": 0,
              "status": 0,
              "kills": 0,
              "cleanCombatOpportunities": 0,
              "firepowerCombatOpportunities": 0,
              "maxExpectedAttack": 0,
              "maxBarrier": 4,
              "maxCurrentBarrier": 4,
              "maxAttackDice": 0,
              "maxSpiritAnimal": 0,
              "maxCultivator": 0,
              "round": 7
            }
          }
        },
        {
          "action": "Floral Patch:row0:trade:anyRelic->restoreBarrier+restoreBarrier+restoreBarrier:choices=1",
          "destination": "Floral Patch",
          "finalVp": 0,
          "finalStatus": 0,
          "kills": 0,
          "combats": 0,
          "combatOpportunities": 0,
          "cleanCombatOpportunities": 0,
          "firepowerCombatOpportunities": 0,
          "maxExpectedAttack": 0,
          "maxBarrier": 4,
          "maxCurrentBarrier": 4,
          "maxAttackDice": 0,
          "maxSpiritAnimal": 0,
          "maxCultivator": 0,
          "maxHealer": 0,
          "maxCleanKillProb": 0,
          "maxFirepowerKillProb": 0,
          "rounds": 6,
          "snapshots": {
            "3": {
              "vp": 0,
              "status": 0,
              "kills": 0,
              "cleanCombatOpportunities": 0,
              "firepowerCombatOpportunities": 0,
              "maxExpectedAttack": 0,
              "maxBarrier": 4,
              "maxCurrentBarrier": 4,
              "maxAttackDice": 0,
              "maxSpiritAnimal": 0,
              "maxCultivator": 0,
              "round": 4
            },
            "6": {
              "vp": 0,
              "status": 0,
              "kills": 0,
              "cleanCombatOpportunities": 0,
              "firepowerCombatOpportunities": 0,
              "maxExpectedAttack": 0,
              "maxBarrier": 4,
              "maxCurrentBarrier": 4,
              "maxAttackDice": 0,
              "maxSpiritAnimal": 0,
              "maxCultivator": 0,
              "round": 7
            }
          }
        },
        {
          "action": "Floral Patch:row0:trade:anyRelic->restoreBarrier+restoreBarrier+restoreBarrier:choices=2",
          "destination": "Floral Patch",
          "finalVp": 0,
          "finalStatus": 0,
          "kills": 0,
          "combats": 0,
          "combatOpportunities": 0,
          "cleanCombatOpportunities": 0,
          "firepowerCombatOpportunities": 0,
          "maxExpectedAttack": 0,
          "maxBarrier": 4,
          "maxCurrentBarrier": 4,
          "maxAttackDice": 0,
          "maxSpiritAnimal": 0,
          "maxCultivator": 0,
          "maxHealer": 0,
          "maxCleanKillProb": 0,
          "maxFirepowerKillProb": 0,
          "rounds": 6,
          "snapshots": {
            "3": {
              "vp": 0,
              "status": 0,
              "kills": 0,
              "cleanCombatOpportunities": 0,
              "firepowerCombatOpportunities": 0,
              "maxExpectedAttack": 0,
              "maxBarrier": 4,
              "maxCurrentBarrier": 4,
              "maxAttackDice": 0,
              "maxSpiritAnimal": 0,
              "maxCultivator": 0,
              "round": 4
            },
            "6": {
              "vp": 0,
              "status": 0,
              "kills": 0,
              "cleanCombatOpportunities": 0,
              "firepowerCombatOpportunities": 0,
              "maxExpectedAttack": 0,
              "maxBarrier": 4,
              "maxCurrentBarrier": 4,
              "maxAttackDice": 0,
              "maxSpiritAnimal": 0,
              "maxCultivator": 0,
              "round": 7
            }
          }
        },
        {
          "action": "Floral Patch:row2:gain:free->rest",
          "destination": "Floral Patch",
          "finalVp": 0,
          "finalStatus": 0,
          "kills": 0,
          "combats": 0,
          "combatOpportunities": 0,
          "cleanCombatOpportunities": 0,
          "firepowerCombatOpportunities": 0,
          "maxExpectedAttack": 0,
          "maxBarrier": 4,
          "maxCurrentBarrier": 4,
          "maxAttackDice": 0,
          "maxSpiritAnimal": 0,
          "maxCultivator": 0,
          "maxHealer": 0,
          "maxCleanKillProb": 0,
          "maxFirepowerKillProb": 0,
          "rounds": 6,
          "snapshots": {
            "3": {
              "vp": 0,
              "status": 0,
              "kills": 0,
              "cleanCombatOpportunities": 0,
              "firepowerCombatOpportunities": 0,
              "maxExpectedAttack": 0,
              "maxBarrier": 4,
              "maxCurrentBarrier": 4,
              "maxAttackDice": 0,
              "maxSpiritAnimal": 0,
              "maxCultivator": 0,
              "round": 4
            },
            "6": {
              "vp": 0,
              "status": 0,
              "kills": 0,
              "cleanCombatOpportunities": 0,
              "firepowerCombatOpportunities": 0,
              "maxExpectedAttack": 0,
              "maxBarrier": 4,
              "maxCurrentBarrier": 4,
              "maxAttackDice": 0,
              "maxSpiritAnimal": 0,
              "maxCultivator": 0,
              "round": 7
            }
          }
        },
        {
          "action": "Floral Patch:row2:gain:free->rest:choices=1",
          "destination": "Floral Patch",
          "finalVp": 0,
          "finalStatus": 0,
          "kills": 0,
          "combats": 0,
          "combatOpportunities": 0,
          "cleanCombatOpportunities": 0,
          "firepowerCombatOpportunities": 0,
          "maxExpectedAttack": 0,
          "maxBarrier": 4,
          "maxCurrentBarrier": 4,
          "maxAttackDice": 0,
          "maxSpiritAnimal": 0,
          "maxCultivator": 0,
          "maxHealer": 0,
          "maxCleanKillProb": 0,
          "maxFirepowerKillProb": 0,
          "rounds": 6,
          "snapshots": {
            "3": {
              "vp": 0,
              "status": 0,
              "kills": 0,
              "cleanCombatOpportunities": 0,
              "firepowerCombatOpportunities": 0,
              "maxExpectedAttack": 0,
              "maxBarrier": 4,
              "maxCurrentBarrier": 4,
              "maxAttackDice": 0,
              "maxSpiritAnimal": 0,
              "maxCultivator": 0,
              "round": 4
            },
            "6": {
              "vp": 0,
              "status": 0,
              "kills": 0,
              "cleanCombatOpportunities": 0,
              "firepowerCombatOpportunities": 0,
              "maxExpectedAttack": 0,
              "maxBarrier": 4,
              "maxCurrentBarrier": 4,
              "maxAttackDice": 0,
              "maxSpiritAnimal": 0,
              "maxCultivator": 0,
              "round": 7
            }
          }
        },
        {
          "action": "Floral Patch:row2:gain:free->rest:choices=2",
          "destination": "Floral Patch",
          "finalVp": 0,
          "finalStatus": 0,
          "kills": 0,
          "combats": 0,
          "combatOpportunities": 0,
          "cleanCombatOpportunities": 0,
          "firepowerCombatOpportunities": 0,
          "maxExpectedAttack": 0,
          "maxBarrier": 4,
          "maxCurrentBarrier": 4,
          "maxAttackDice": 0,
          "maxSpiritAnimal": 0,
          "maxCultivator": 0,
          "maxHealer": 0,
          "maxCleanKillProb": 0,
          "maxFirepowerKillProb": 0,
          "rounds": 6,
          "snapshots": {
            "3": {
              "vp": 0,
              "status": 0,
              "kills": 0,
              "cleanCombatOpportunities": 0,
              "firepowerCombatOpportunities": 0,
              "maxExpectedAttack": 0,
              "maxBarrier": 4,
              "maxCurrentBarrier": 4,
              "maxAttackDice": 0,
              "maxSpiritAnimal": 0,
              "maxCultivator": 0,
              "round": 4
            },
            "6": {
              "vp": 0,
              "status": 0,
              "kills": 0,
              "cleanCombatOpportunities": 0,
              "firepowerCombatOpportunities": 0,
              "maxExpectedAttack": 0,
              "maxBarrier": 4,
              "maxCurrentBarrier": 4,
              "maxAttackDice": 0,
              "maxSpiritAnimal": 0,
              "maxCultivator": 0,
              "round": 7
            }
          }
        }
      ]
    },
    {
      "id": "g0-Red-r7-1",
      "game": 0,
      "seat": "Red",
      "round": 7,
      "destination": "Floral Patch",
      "playerVp": 0,
      "playerStatus": 0,
      "legalActions": 6,
      "heuristicAction": "Floral Patch:row0:trade:anyRelic->restoreBarrier+restoreBarrier+restoreBarrier",
      "bestAction": "Floral Patch:row0:trade:anyRelic->restoreBarrier+restoreBarrier+restoreBarrier",
      "bestScoreDelta": 0,
      "bestVpDelta": 0,
      "bestCleanOpportunityDelta": 0,
      "bestFirepowerOpportunityDelta": 0,
      "bestExpectedAttackDelta": 0,
      "bestBarrierDelta": 0,
      "bestSpiritAnimalDelta": 0,
      "branches": [
        {
          "action": "Floral Patch:row0:trade:anyRelic->restoreBarrier+restoreBarrier+restoreBarrier",
          "destination": "Floral Patch",
          "finalVp": 0,
          "finalStatus": 0,
          "kills": 0,
          "combats": 0,
          "combatOpportunities": 0,
          "cleanCombatOpportunities": 0,
          "firepowerCombatOpportunities": 0,
          "maxExpectedAttack": 0,
          "maxBarrier": 4,
          "maxCurrentBarrier": 4,
          "maxAttackDice": 0,
          "maxSpiritAnimal": 0,
          "maxCultivator": 0,
          "maxHealer": 0,
          "maxCleanKillProb": 0,
          "maxFirepowerKillProb": 0,
          "rounds": 6,
          "snapshots": {
            "3": {
              "vp": 0,
              "status": 0,
              "kills": 0,
              "cleanCombatOpportunities": 0,
              "firepowerCombatOpportunities": 0,
              "maxExpectedAttack": 0,
              "maxBarrier": 4,
              "maxCurrentBarrier": 4,
              "maxAttackDice": 0,
              "maxSpiritAnimal": 0,
              "maxCultivator": 0,
              "round": 10
            },
            "6": {
              "vp": 0,
              "status": 0,
              "kills": 0,
              "cleanCombatOpportunities": 0,
              "firepowerCombatOpportunities": 0,
              "maxExpectedAttack": 0,
              "maxBarrier": 4,
              "maxCurrentBarrier": 4,
              "maxAttackDice": 0,
              "maxSpiritAnimal": 0,
              "maxCultivator": 0,
              "round": 13
            }
          }
        },
        {
          "action": "Floral Patch:row0:trade:anyRelic->restoreBarrier+restoreBarrier+restoreBarrier:choices=1",
          "destination": "Floral Patch",
          "finalVp": 0,
          "finalStatus": 0,
          "kills": 0,
          "combats": 0,
          "combatOpportunities": 0,
          "cleanCombatOpportunities": 0,
          "firepowerCombatOpportunities": 0,
          "maxExpectedAttack": 0,
          "maxBarrier": 4,
          "maxCurrentBarrier": 4,
          "maxAttackDice": 0,
          "maxSpiritAnimal": 0,
          "maxCultivator": 0,
          "maxHealer": 0,
          "maxCleanKillProb": 0,
          "maxFirepowerKillProb": 0,
          "rounds": 6,
          "snapshots": {
            "3": {
              "vp": 0,
              "status": 0,
              "kills": 0,
              "cleanCombatOpportunities": 0,
              "firepowerCombatOpportunities": 0,
              "maxExpectedAttack": 0,
              "maxBarrier": 4,
              "maxCurrentBarrier": 4,
              "maxAttackDice": 0,
              "maxSpiritAnimal": 0,
              "maxCultivator": 0,
              "round": 10
            },
            "6": {
              "vp": 0,
              "status": 0,
              "kills": 0,
              "cleanCombatOpportunities": 0,
              "firepowerCombatOpportunities": 0,
              "maxExpectedAttack": 0,
              "maxBarrier": 4,
              "maxCurrentBarrier": 4,
              "maxAttackDice": 0,
              "maxSpiritAnimal": 0,
              "maxCultivator": 0,
              "round": 13
            }
          }
        },
        {
          "action": "Floral Patch:row0:trade:anyRelic->restoreBarrier+restoreBarrier+restoreBarrier:choices=2",
          "destination": "Floral Patch",
          "finalVp": 0,
          "finalStatus": 0,
          "kills": 0,
          "combats": 0,
          "combatOpportunities": 0,
          "cleanCombatOpportunities": 0,
          "firepowerCombatOpportunities": 0,
          "maxExpectedAttack": 0,
          "maxBarrier": 4,
          "maxCurrentBarrier": 4,
          "maxAttackDice": 0,
          "maxSpiritAnimal": 0,
          "maxCultivator": 0,
          "maxHealer": 0,
          "maxCleanKillProb": 0,
          "maxFirepowerKillProb": 0,
          "rounds": 6,
          "snapshots": {
            "3": {
              "vp": 0,
              "status": 0,
              "kills": 0,
              "cleanCombatOpportunities": 0,
              "firepowerCombatOpportunities": 0,
              "maxExpectedAttack": 0,
              "maxBarrier": 4,
              "maxCurrentBarrier": 4,
              "maxAttackDice": 0,
              "maxSpiritAnimal": 0,
              "maxCultivator": 0,
              "round": 10
            },
            "6": {
              "vp": 0,
              "status": 0,
              "kills": 0,
              "cleanCombatOpportunities": 0,
              "firepowerCombatOpportunities": 0,
              "maxExpectedAttack": 0,
              "maxBarrier": 4,
              "maxCurrentBarrier": 4,
              "maxAttackDice": 0,
              "maxSpiritAnimal": 0,
              "maxCultivator": 0,
              "round": 13
            }
          }
        },
        {
          "action": "Floral Patch:row2:gain:free->rest",
          "destination": "Floral Patch",
          "finalVp": 0,
          "finalStatus": 0,
          "kills": 0,
          "combats": 0,
          "combatOpportunities": 0,
          "cleanCombatOpportunities": 0,
          "firepowerCombatOpportunities": 0,
          "maxExpectedAttack": 0,
          "maxBarrier": 4,
          "maxCurrentBarrier": 4,
          "maxAttackDice": 0,
          "maxSpiritAnimal": 0,
          "maxCultivator": 0,
          "maxHealer": 0,
          "maxCleanKillProb": 0,
          "maxFirepowerKillProb": 0,
          "rounds": 6,
          "snapshots": {
            "3": {
              "vp": 0,
              "status": 0,
              "kills": 0,
              "cleanCombatOpportunities": 0,
              "firepowerCombatOpportunities": 0,
              "maxExpectedAttack": 0,
              "maxBarrier": 4,
              "maxCurrentBarrier": 4,
              "maxAttackDice": 0,
              "maxSpiritAnimal": 0,
              "maxCultivator": 0,
              "round": 10
            },
            "6": {
              "vp": 0,
              "status": 0,
              "kills": 0,
              "cleanCombatOpportunities": 0,
              "firepowerCombatOpportunities": 0,
              "maxExpectedAttack": 0,
              "maxBarrier": 4,
              "maxCurrentBarrier": 4,
              "maxAttackDice": 0,
              "maxSpiritAnimal": 0,
              "maxCultivator": 0,
              "round": 13
            }
          }
        },
        {
          "action": "Floral Patch:row2:gain:free->rest:choices=1",
          "destination": "Floral Patch",
          "finalVp": 0,
          "finalStatus": 0,
          "kills": 0,
          "combats": 0,
          "combatOpportunities": 0,
          "cleanCombatOpportunities": 0,
          "firepowerCombatOpportunities": 0,
          "maxExpectedAttack": 0,
          "maxBarrier": 4,
          "maxCurrentBarrier": 4,
          "maxAttackDice": 0,
          "maxSpiritAnimal": 0,
          "maxCultivator": 0,
          "maxHealer": 0,
          "maxCleanKillProb": 0,
          "maxFirepowerKillProb": 0,
          "rounds": 6,
          "snapshots": {
            "3": {
              "vp": 0,
              "status": 0,
              "kills": 0,
              "cleanCombatOpportunities": 0,
              "firepowerCombatOpportunities": 0,
              "maxExpectedAttack": 0,
              "maxBarrier": 4,
              "maxCurrentBarrier": 4,
              "maxAttackDice": 0,
              "maxSpiritAnimal": 0,
              "maxCultivator": 0,
              "round": 10
            },
            "6": {
              "vp": 0,
              "status": 0,
              "kills": 0,
              "cleanCombatOpportunities": 0,
              "firepowerCombatOpportunities": 0,
              "maxExpectedAttack": 0,
              "maxBarrier": 4,
              "maxCurrentBarrier": 4,
              "maxAttackDice": 0,
              "maxSpiritAnimal": 0,
              "maxCultivator": 0,
              "round": 13
            }
          }
        },
        {
          "action": "Floral Patch:row2:gain:free->rest:choices=2",
          "destination": "Floral Patch",
          "finalVp": 0,
          "finalStatus": 0,
          "kills": 0,
          "combats": 0,
          "combatOpportunities": 0,
          "cleanCombatOpportunities": 0,
          "firepowerCombatOpportunities": 0,
          "maxExpectedAttack": 0,
          "maxBarrier": 4,
          "maxCurrentBarrier": 4,
          "maxAttackDice": 0,
          "maxSpiritAnimal": 0,
          "maxCultivator": 0,
          "maxHealer": 0,
          "maxCleanKillProb": 0,
          "maxFirepowerKillProb": 0,
          "rounds": 6,
          "snapshots": {
            "3": {
              "vp": 0,
              "status": 0,
              "kills": 0,
              "cleanCombatOpportunities": 0,
              "firepowerCombatOpportunities": 0,
              "maxExpectedAttack": 0,
              "maxBarrier": 4,
              "maxCurrentBarrier": 4,
              "maxAttackDice": 0,
              "maxSpiritAnimal": 0,
              "maxCultivator": 0,
              "round": 10
            },
            "6": {
              "vp": 0,
              "status": 0,
              "kills": 0,
              "cleanCombatOpportunities": 0,
              "firepowerCombatOpportunities": 0,
              "maxExpectedAttack": 0,
              "maxBarrier": 4,
              "maxCurrentBarrier": 4,
              "maxAttackDice": 0,
              "maxSpiritAnimal": 0,
              "maxCultivator": 0,
              "round": 13
            }
          }
        }
      ]
    },
    {
      "id": "g0-Red-r13-2",
      "game": 0,
      "seat": "Red",
      "round": 13,
      "destination": "Floral Patch",
      "playerVp": 0,
      "playerStatus": 0,
      "legalActions": 3,
      "heuristicAction": "Floral Patch:row2:gain:free->rest",
      "bestAction": "Floral Patch:row2:gain:free->rest",
      "bestScoreDelta": 0,
      "bestVpDelta": 0,
      "bestCleanOpportunityDelta": 0,
      "bestFirepowerOpportunityDelta": 0,
      "bestExpectedAttackDelta": 0,
      "bestBarrierDelta": 0,
      "bestSpiritAnimalDelta": 0,
      "branches": [
        {
          "action": "Floral Patch:row2:gain:free->rest",
          "destination": "Floral Patch",
          "finalVp": 0,
          "finalStatus": 0,
          "kills": 0,
          "combats": 0,
          "combatOpportunities": 0,
          "cleanCombatOpportunities": 0,
          "firepowerCombatOpportunities": 0,
          "maxExpectedAttack": 0,
          "maxBarrier": 4,
          "maxCurrentBarrier": 4,
          "maxAttackDice": 0,
          "maxSpiritAnimal": 0,
          "maxCultivator": 0,
          "maxHealer": 0,
          "maxCleanKillProb": 0,
          "maxFirepowerKillProb": 0,
          "rounds": 6,
          "snapshots": {
            "3": {
              "vp": 0,
              "status": 0,
              "kills": 0,
              "cleanCombatOpportunities": 0,
              "firepowerCombatOpportunities": 0,
              "maxExpectedAttack": 0,
              "maxBarrier": 4,
              "maxCurrentBarrier": 4,
              "maxAttackDice": 0,
              "maxSpiritAnimal": 0,
              "maxCultivator": 0,
              "round": 16
            },
            "6": {
              "vp": 0,
              "status": 0,
              "kills": 0,
              "cleanCombatOpportunities": 0,
              "firepowerCombatOpportunities": 0,
              "maxExpectedAttack": 0,
              "maxBarrier": 4,
              "maxCurrentBarrier": 4,
              "maxAttackDice": 0,
              "maxSpiritAnimal": 0,
              "maxCultivator": 0,
              "round": 19
            }
          }
        },
        {
          "action": "Floral Patch:row2:gain:free->rest:choices=1",
          "destination": "Floral Patch",
          "finalVp": 0,
          "finalStatus": 0,
          "kills": 0,
          "combats": 0,
          "combatOpportunities": 0,
          "cleanCombatOpportunities": 0,
          "firepowerCombatOpportunities": 0,
          "maxExpectedAttack": 0,
          "maxBarrier": 4,
          "maxCurrentBarrier": 4,
          "maxAttackDice": 0,
          "maxSpiritAnimal": 0,
          "maxCultivator": 0,
          "maxHealer": 0,
          "maxCleanKillProb": 0,
          "maxFirepowerKillProb": 0,
          "rounds": 6,
          "snapshots": {
            "3": {
              "vp": 0,
              "status": 0,
              "kills": 0,
              "cleanCombatOpportunities": 0,
              "firepowerCombatOpportunities": 0,
              "maxExpectedAttack": 0,
              "maxBarrier": 4,
              "maxCurrentBarrier": 4,
              "maxAttackDice": 0,
              "maxSpiritAnimal": 0,
              "maxCultivator": 0,
              "round": 16
            },
            "6": {
              "vp": 0,
              "status": 0,
              "kills": 0,
              "cleanCombatOpportunities": 0,
              "firepowerCombatOpportunities": 0,
              "maxExpectedAttack": 0,
              "maxBarrier": 4,
              "maxCurrentBarrier": 4,
              "maxAttackDice": 0,
              "maxSpiritAnimal": 0,
              "maxCultivator": 0,
              "round": 19
            }
          }
        },
        {
          "action": "Floral Patch:row2:gain:free->rest:choices=2",
          "destination": "Floral Patch",
          "finalVp": 0,
          "finalStatus": 0,
          "kills": 0,
          "combats": 0,
          "combatOpportunities": 0,
          "cleanCombatOpportunities": 0,
          "firepowerCombatOpportunities": 0,
          "maxExpectedAttack": 0,
          "maxBarrier": 4,
          "maxCurrentBarrier": 4,
          "maxAttackDice": 0,
          "maxSpiritAnimal": 0,
          "maxCultivator": 0,
          "maxHealer": 0,
          "maxCleanKillProb": 0,
          "maxFirepowerKillProb": 0,
          "rounds": 6,
          "snapshots": {
            "3": {
              "vp": 0,
              "status": 0,
              "kills": 0,
              "cleanCombatOpportunities": 0,
              "firepowerCombatOpportunities": 0,
              "maxExpectedAttack": 0,
              "maxBarrier": 4,
              "maxCurrentBarrier": 4,
              "maxAttackDice": 0,
              "maxSpiritAnimal": 0,
              "maxCultivator": 0,
              "round": 16
            },
            "6": {
              "vp": 0,
              "status": 0,
              "kills": 0,
              "cleanCombatOpportunities": 0,
              "firepowerCombatOpportunities": 0,
              "maxExpectedAttack": 0,
              "maxBarrier": 4,
              "maxCurrentBarrier": 4,
              "maxAttackDice": 0,
              "maxSpiritAnimal": 0,
              "maxCultivator": 0,
              "round": 19
            }
          }
        }
      ]
    },
    {
      "id": "g0-Red-r20-3",
      "game": 0,
      "seat": "Red",
      "round": 20,
      "destination": "Floral Patch",
      "playerVp": 0,
      "playerStatus": 0,
      "legalActions": 3,
      "heuristicAction": "Floral Patch:row2:gain:free->rest",
      "bestAction": "Floral Patch:row2:gain:free->rest",
      "bestScoreDelta": 0,
      "bestVpDelta": 0,
      "bestCleanOpportunityDelta": 0,
      "bestFirepowerOpportunityDelta": 0,
      "bestExpectedAttackDelta": 0,
      "bestBarrierDelta": 0,
      "bestSpiritAnimalDelta": 0,
      "branches": [
        {
          "action": "Floral Patch:row2:gain:free->rest",
          "destination": "Floral Patch",
          "finalVp": 0,
          "finalStatus": 0,
          "kills": 0,
          "combats": 0,
          "combatOpportunities": 0,
          "cleanCombatOpportunities": 0,
          "firepowerCombatOpportunities": 0,
          "maxExpectedAttack": 0.6666666666666666,
          "maxBarrier": 4,
          "maxCurrentBarrier": 4,
          "maxAttackDice": 1,
          "maxSpiritAnimal": 0,
          "maxCultivator": 2,
          "maxHealer": 0,
          "maxCleanKillProb": 0,
          "maxFirepowerKillProb": 0,
          "rounds": 6,
          "snapshots": {
            "3": {
              "vp": 0,
              "status": 0,
              "kills": 0,
              "cleanCombatOpportunities": 0,
              "firepowerCombatOpportunities": 0,
              "maxExpectedAttack": 0.6666666666666666,
              "maxBarrier": 4,
              "maxCurrentBarrier": 4,
              "maxAttackDice": 1,
              "maxSpiritAnimal": 0,
              "maxCultivator": 2,
              "round": 23
            },
            "6": {
              "vp": 0,
              "status": 0,
              "kills": 0,
              "cleanCombatOpportunities": 0,
              "firepowerCombatOpportunities": 0,
              "maxExpectedAttack": 0.6666666666666666,
              "maxBarrier": 4,
              "maxCurrentBarrier": 4,
              "maxAttackDice": 1,
              "maxSpiritAnimal": 0,
              "maxCultivator": 2,
              "round": 26
            }
          }
        },
        {
          "action": "Floral Patch:row2:gain:free->rest:choices=1",
          "destination": "Floral Patch",
          "finalVp": 0,
          "finalStatus": 0,
          "kills": 0,
          "combats": 0,
          "combatOpportunities": 0,
          "cleanCombatOpportunities": 0,
          "firepowerCombatOpportunities": 0,
          "maxExpectedAttack": 0.6666666666666666,
          "maxBarrier": 4,
          "maxCurrentBarrier": 4,
          "maxAttackDice": 1,
          "maxSpiritAnimal": 0,
          "maxCultivator": 2,
          "maxHealer": 0,
          "maxCleanKillProb": 0,
          "maxFirepowerKillProb": 0,
          "rounds": 6,
          "snapshots": {
            "3": {
              "vp": 0,
              "status": 0,
              "kills": 0,
              "cleanCombatOpportunities": 0,
              "firepowerCombatOpportunities": 0,
              "maxExpectedAttack": 0.6666666666666666,
              "maxBarrier": 4,
              "maxCurrentBarrier": 4,
              "maxAttackDice": 1,
              "maxSpiritAnimal": 0,
              "maxCultivator": 2,
              "round": 23
            },
            "6": {
              "vp": 0,
              "status": 0,
              "kills": 0,
              "cleanCombatOpportunities": 0,
              "firepowerCombatOpportunities": 0,
              "maxExpectedAttack": 0.6666666666666666,
              "maxBarrier": 4,
              "maxCurrentBarrier": 4,
              "maxAttackDice": 1,
              "maxSpiritAnimal": 0,
              "maxCultivator": 2,
              "round": 26
            }
          }
        },
        {
          "action": "Floral Patch:row2:gain:free->rest:choices=2",
          "destination": "Floral Patch",
          "finalVp": 0,
          "finalStatus": 0,
          "kills": 0,
          "combats": 0,
          "combatOpportunities": 0,
          "cleanCombatOpportunities": 0,
          "firepowerCombatOpportunities": 0,
          "maxExpectedAttack": 0.6666666666666666,
          "maxBarrier": 4,
          "maxCurrentBarrier": 4,
          "maxAttackDice": 1,
          "maxSpiritAnimal": 0,
          "maxCultivator": 2,
          "maxHealer": 0,
          "maxCleanKillProb": 0,
          "maxFirepowerKillProb": 0,
          "rounds": 6,
          "snapshots": {
            "3": {
              "vp": 0,
              "status": 0,
              "kills": 0,
              "cleanCombatOpportunities": 0,
              "firepowerCombatOpportunities": 0,
              "maxExpectedAttack": 0.6666666666666666,
              "maxBarrier": 4,
              "maxCurrentBarrier": 4,
              "maxAttackDice": 1,
              "maxSpiritAnimal": 0,
              "maxCultivator": 2,
              "round": 23
            },
            "6": {
              "vp": 0,
              "status": 0,
              "kills": 0,
              "cleanCombatOpportunities": 0,
              "firepowerCombatOpportunities": 0,
              "maxExpectedAttack": 0.6666666666666666,
              "maxBarrier": 4,
              "maxCurrentBarrier": 4,
              "maxAttackDice": 1,
              "maxSpiritAnimal": 0,
              "maxCultivator": 2,
              "round": 26
            }
          }
        }
      ]
    }
  ]
}
